logium/__init__.py
logium-1.2.dist-info/METADATA
logium-1.2.dist-info/WHEEL
logium-1.2.dist-info/top_level.txt
logium-1.2.dist-info/RECORD
