Metadata-Version: 2.1
Name: logium
Version: 1.2
Summary: This is a test version of my logger
Author: N0rmalUser
Author-email: normalstudio25@gmail.com
